lacium_flower/__init__.py
lacium_flower/abordagem1.py
lacium_flower/abordagem2.py
lacium_flower/abordagem3.py
lacium_flower/avaliacao.py
lacium_flower-0.1.0.dist-info/LICENSE
lacium_flower-0.1.0.dist-info/METADATA
lacium_flower-0.1.0.dist-info/WHEEL
lacium_flower-0.1.0.dist-info/top_level.txt
lacium_flower-0.1.0.dist-info/RECORD
