Metadata-Version: 2.1
Name: lacium-flower
Version: 0.1.0
Summary: Biblioteca para cálculo de similaridade fonológica e semântica
Home-page: https://github.com/usuario/lacium-flower
Author: Geraldo Gomes
Author-email: Geraldo Gomes <ggc4@cin.ufpe.br>
License: MIT License
Project-URL: Homepage, https://github.com/usuario/lacium-flower
Classifier: Programming Language :: Python :: 3
Classifier: License :: OSI Approved :: MIT License
Classifier: Development Status :: 4 - Beta
Classifier: Intended Audience :: Developers
Classifier: Operating System :: OS Independent
Requires-Python: >=3.6
License-File: LICENSE
